{
    "skills": [
        "Clinical data analyst with 3 years of experience analyzing patient and clinical trial Clinical Data Analysis",
        "datasets to advance medical research and improve care outcomes. Skilled in data Data Validation",
        "Research Support",
        "validation, clinical reporting, and research support. Strong knowledge of clinical",
        "CDISC/SDTM",
        "workflows, medical terminology, and regulatory data standards including ICH-GCP and",
        "Regulatory Compliance",
        "CDISC.",
        "Trial Reporting"
    ],
    "experience": [
        {
            "role_header": "Brigham and Women's Hospital \u00b7 Mar 2022 \u2013 Present SAS",
            "duties": [
                "Analyzed clinical trial data for Phase II/III oncology studies involving 800+ patients. R",
                "Validated and cleaned clinical datasets ensuring 99.8% data integrity before lock. REDCap",
                "Oracle Clinical",
                "Generated treatment outcome reports used by principal investigators for publications.",
                "Excel",
                "Ensured CDISC SDTM compliance across all data submissions to the FDA.",
                "Medidata Rave",
                "Research Data Coordinator"
            ]
        },
        {
            "role_header": "Massachusetts General Hospital \u00b7 Jul 2021 \u2013 Feb 2022 English (Fluent)",
            "duties": [
                "Supported research teams with data extraction from REDCap and Epic clinical Twi (Native)",
                "systems.",
                "Reconciled discrepancies in patient lab and imaging data across 12 active studies. Research Methodology",
                "Prepared data summaries and slide decks for monthly sponsor review meetings. Critical Thinking",
                "Cross-functional"
            ]
        }
    ],
    "education": [
        "Collaboration",
        "M.S. in Biomedical Informatics",
        "Boston University \u00b7 2021",
        "B.S. in Biochemistry",
        "University of Ghana \u00b7 2019"
    ],
    "projects": [],
    "certifications": [
        "Certified Clinical Data Manager (CCDM) \u2013 SCDM (2023)",
        "ICH-GCP Training Certificate (2022)",
        "CDISC SDTM Fundamentals (2022)"
    ],
    "achievements": [],
    "other": [
        "Daniel Osei",
        "Clinical Data Analyst",
        "daniel.osei@email.com | +1 (617) 555-0293 | Boston, MA | linkedin.com/in/danielosei",
        "HEADER: PROFESSIONAL SUMMARY",
        "HEADER: CORE SKILLS",
        "HEADER: WORK EXPERIENCE",
        "&",
        "Clinical Data Analyst",
        "HEADER: EDUCATION",
        "HEADER: CERTIFICATIONS"
    ]
}